molecule_wrapper/__init__.py
molecule_wrapper/cli.py
molecule_wrapper/galaxy.py
molecule_wrapper/io.py
tests/__init__.py
tests/test_yaml.py
molecule_galaxy_wrapper-0.0.4.dist-info/LICENSE
molecule_galaxy_wrapper-0.0.4.dist-info/METADATA
molecule_galaxy_wrapper-0.0.4.dist-info/WHEEL
molecule_galaxy_wrapper-0.0.4.dist-info/entry_points.txt
molecule_galaxy_wrapper-0.0.4.dist-info/top_level.txt
molecule_galaxy_wrapper-0.0.4.dist-info/RECORD
