Metadata-Version: 2.1
Name: molecule-galaxy-wrapper
Version: 0.0.4
Summary: A wrapper for ansible-galaxy that allows you to define role dependencies inside a requirements.yml
Home-page: https://github.com/bernardoVale/molecule-galaxy-wrapper
Author: Bernardo Vale
Author-email: bernardosilveiravale@gmail.com
License: UNKNOWN
Keywords: molecule ansible ansible-galaxy galaxy dependency
Platform: UNKNOWN
Classifier: Programming Language :: Python :: 3
Classifier: Programming Language :: Python :: 2.6
Classifier: Programming Language :: Python :: 2.7
Classifier: License :: OSI Approved :: Apache Software License
Classifier: Operating System :: OS Independent
Requires-Dist: ruamel.yaml (>=0.15.87)
